ansys/grantami/jobqueue/__init__.py
ansys/grantami/jobqueue/_connection.py
ansys/grantami/jobqueue/_logger.py
ansys/grantami/jobqueue/_models.py
ansys/grantami/jobqueue/py.typed
ansys_grantami_jobqueue-1.2.0.dist-info/AUTHORS
ansys_grantami_jobqueue-1.2.0.dist-info/LICENSE
ansys_grantami_jobqueue-1.2.0.dist-info/METADATA
ansys_grantami_jobqueue-1.2.0.dist-info/WHEEL
ansys_grantami_jobqueue-1.2.0.dist-info/RECORD
