Metadata-Version: 2.3
Name: ansys-grantami-jobqueue
Version: 1.2.0
Summary: A python wrapper for the Granta MI Job Queue API
License: MIT
Author: ANSYS, Inc.
Author-email: pyansys.core@ansys.com
Maintainer: ANSYS, Inc.
Maintainer-email: pyansys.core@ansys.com
Requires-Python: >=3.10,<4.0
Classifier: Development Status :: 5 - Production/Stable
Classifier: License :: OSI Approved :: MIT License
Classifier: Operating System :: OS Independent
Classifier: Programming Language :: Python :: 3
Classifier: Programming Language :: Python :: 3.10
Classifier: Programming Language :: Python :: 3.11
Classifier: Programming Language :: Python :: 3.12
Classifier: Programming Language :: Python :: 3.13
Requires-Dist: ansys-grantami-serverapi-openapi (>=5.0,<6.0)
Requires-Dist: ansys-openapi-common (>=2.0.0,<3.0.0)
Project-URL: Documentation, https://jobqueue.grantami.docs.pyansys.com
Project-URL: Repository, https://github.com/ansys/grantami-jobqueue
